bubbling_editor/__init__.py
bubbling_editor/bubbling_editor_image.py
bubbling_editor/bus.py
bubbling_editor/editor.py
bubbling_editor/gui.py
bubbling_editor/helpers.py
bubbling_editor/misc.py
bubbling_editor/statechart.py
bubbling_editor-0.0.3.1.dist-info/LICENSE
bubbling_editor-0.0.3.1.dist-info/METADATA
bubbling_editor-0.0.3.1.dist-info/WHEEL
bubbling_editor-0.0.3.1.dist-info/entry_points.txt
bubbling_editor-0.0.3.1.dist-info/top_level.txt
bubbling_editor-0.0.3.1.dist-info/RECORD
