Metadata-Version: 2.1
Name: bubbling-editor
Version: 0.0.3.1
Summary: Simple Tkinter image bubbling editor
Author: vkalyvayut-roboty-a-ne-chelovek
License: This is free and unencumbered software released into the public domain.
Project-URL: Homepage, https://github.com/vkalyvayut-roboty-a-ne-chelovek/bubbling-editor
Project-URL: Issues, https://github.com/vkalyvayut-roboty-a-ne-chelovek/bubbling-editor/issues
Keywords: tkinter,bubbling,image-editor
Classifier: Programming Language :: Python
Classifier: Development Status :: 4 - Beta
Classifier: Intended Audience :: End Users/Desktop
Classifier: License :: OSI Approved :: The Unlicense (Unlicense)
Classifier: Operating System :: OS Independent
Requires-Python: >=3.10
License-File: LICENSE
Requires-Dist: miros
Requires-Dist: pillow
